{
  "Workflows": [
    {
      "Path": null,
      "SortBy": 0,
      "VariablesSectionElementsOrder": [],
      "ArgumentsSectionElementsOrder": null,
      "ConstantsSectionElementsOrder": [],
      "AddedNamespaces": null
    },
    {
      "Path": "Main.xaml",
      "SortBy": 0,
      "VariablesSectionElementsOrder": [
        "PADWindowSelector&Sequence_1",
        "PADType&Sequence_1",
        "Choice&Sequence_1",
        "PADOpen&Sequence_1",
        "FolderInfo&Sequence_1",
        "SubflowNameDT&Sequence_12",
        "FlowName&Sequence_12",
        "RowIndex&Sequence_1",
        "SubflowName&Sequence_13",
        "ClipboardData&Sequence_13",
        "NewFlowDataFile&Sequence_13",
        "ListOfFlowNames&Sequence_1",
        "BackupPath&Sequence_1"
      ],
      "ArgumentsSectionElementsOrder": [],
      "ConstantsSectionElementsOrder": [],
      "AddedNamespaces": null
    },
    {
      "Path": "PAD Actions/PAD_OpenWorkflow.xaml",
      "SortBy": 0,
      "VariablesSectionElementsOrder": [
        "DesignerOpen&Sequence_1"
      ],
      "ArgumentsSectionElementsOrder": [
        "PADWindowSelector",
        "FlowName",
        "RowIndex"
      ],
      "ConstantsSectionElementsOrder": [],
      "AddedNamespaces": null
    },
    {
      "Path": "PAD Actions/PAD_ExtractSubflowData.xaml",
      "SortBy": 0,
      "VariablesSectionElementsOrder": [],
      "ArgumentsSectionElementsOrder": [
        "PADWindowSelector",
        "ClipboardData",
        "SubflowName",
        "FlowName"
      ],
      "ConstantsSectionElementsOrder": [],
      "AddedNamespaces": null
    },
    {
      "Path": "PAD Actions/PAD_RetrieveSubflowNamesAsTable.xaml",
      "SortBy": 0,
      "VariablesSectionElementsOrder": [
        "SubflowPanelContents&Sequence_1"
      ],
      "ArgumentsSectionElementsOrder": [
        "PADWindowSelector",
        "SubflowNameDT",
        "FlowName"
      ],
      "ConstantsSectionElementsOrder": [],
      "AddedNamespaces": null
    },
    {
      "Path": "PAD Actions/PAD_CloseWorkflow.xaml",
      "SortBy": 0,
      "VariablesSectionElementsOrder": [
        "SubflowPanelContents&Sequence_2"
      ],
      "ArgumentsSectionElementsOrder": [
        "PADWindowSelector",
        "FlowName"
      ],
      "ConstantsSectionElementsOrder": [],
      "AddedNamespaces": null
    },
    {
      "Path": "Test.xaml",
      "SortBy": 0,
      "VariablesSectionElementsOrder": [],
      "ArgumentsSectionElementsOrder": [],
      "ConstantsSectionElementsOrder": [],
      "AddedNamespaces": null
    }
  ]
}